utils/FourierCommon.py
utils/FourierUtils.py
utils/__init__.py
utils/_version.py
utils/bissection.py
utils/changelog.md
utils/commonInputOutput.py
utils/conftest.py
utils/displayStandards.py
utils/eventHandler.py
utils/gears.py
utils/glob_colors.py
utils/handler3D.py
utils/jupy_utils.py
utils/materialManager.py
utils/menus.py
utils/newtonRaphson.py
utils/physicsConstants.py
utils/printStandards.py
utils/pytest.ini
utils/pytest_util.py
utils/regionManager.py
utils/statistics.py
utils/struct_meca.py
utils/symex.py
utils/materials/AlAs.py
utils/materials/GaAs.py
utils/materials/Ge.py
utils/materials/InAs.py
utils/materials/Si.py
utils/materials/make_df_mat.py
utils/materials/materials.pkl
TarikDrevonUtils-1.4.dist-info/LICENSE
TarikDrevonUtils-1.4.dist-info/METADATA
TarikDrevonUtils-1.4.dist-info/WHEEL
TarikDrevonUtils-1.4.dist-info/top_level.txt
TarikDrevonUtils-1.4.dist-info/RECORD
