Metadata-Version: 2.1
Name: TarikDrevonUtils
Version: 1.4
Summary: some display utilities and others
Home-page: UNKNOWN
Author: Tarik Ronan Drevon
Author-email: ronandrevon@gmail.com
License: UNKNOWN
Platform: UNKNOWN
Classifier: Programming Language :: Python :: 3
Classifier: License :: OSI Approved :: MIT License 
Classifier: Operating System :: OS Independent
Requires-Python: >=3.6
Requires-Dist: colorama
Requires-Dist: matplotlib
Requires-Dist: numpy
Requires-Dist: pandas
Requires-Dist: pillow
Requires-Dist: pytest
Requires-Dist: pytest-html
Requires-Dist: scipy
